{"developer_index.md":"19e1fcb9","developer_l10n.md":"a9108117","en_us_developer_index.md":"21beeda4","en_us_developer_l10n.md":"7107284d","en_us_guide_dashboard.md":"c121522f","en_us_guide_dashboardq.md":"95264178","en_us_guide_docker_build.md":"14dc4807","en_us_guide_docker_precheck.md":"dd06bef9","en_us_guide_docker_qa.md":"32f1aa8d","case_case1.md":"9aa7e0b8","en_us_guide_docker_thanks.md":"18e406e3","case_case4.md":"c116a73b","en_us_guide_docker_install.md":"05d0b68b","case_case2.md":"406cfd46","case_case6.md":"ae846254","case_case7.md":"68c3a51e","case_case5.md":"a2993300","en_us_guide_pve_qa.md":"07ac8edd","case_index.md":"1abf495b","guide_dashboardq.md":"f12bc993","guide_dashboard.md":"78153b08","guide_docker_precheck.md":"33871177","guide_docker_build.md":"c0e598ef","en_us_guide_lxd_extra_config.md":"b5b7a90d","en_us_guide_lxd_install.md":"1b2d2a80","en_us_guide_lxd_lxc.md":"405bc32e","en_us_guide_lxd_precheck.md":"7def3107","en_us_guide_lxd_qa.md":"3b5c7512","en_us_guide_lxd_thanks.md":"4be6473f","en_us_guide_pve_custom.md":"92199b48","en_us_guide_pve_install.md":"e98c22ce","en_us_guide_pve_kvm.md":"81057d31","guide_lxd_qa.md":"425091ec","guide_lxd_thanks.md":"304bc00a","guide_pve_custom.md":"00973135","guide_pve_install.md":"2f8593bd","guide_pve_kvm.md":"328de829","guide_pve_lxc.md":"ce5bdfa3","guide_pve_precheck.md":"b9c30d19","guide_lxd_precheck.md":"930662e7","en_us_guide_pve_thanks.md":"fdcb6ee4","guide_docker_qa.md":"0d445ab2","guide_lxd_custom.md":"bb9ae7c4","en_us_guide_pve_precheck.md":"33c81765","en_us_index.md":"2d9892bf","guide_docker_install.md":"c146d919","guide_docker_thanks.md":"520dfd95","guide_lxd_lxc.md":"e8d32ac2","en_us_guide_lxd_custom.md":"597e4344","index.md":"c769b678","case_case3.md":"4ddb96e0","en_us_guide_pve_lxc.md":"85505e54","guide_lxd_extra_config.md":"06041b4e","guide_lxd_install.md":"5f7067ef","guide_docker_custom.md":"53ba9226","en_us_guide_docker_custom.md":"27ec6d8d","guide_pve_thanks.md":"23edcabf","guide_pve_qa.md":"c83ed412"}
