{"case_case1.md":"Bwl59Dms","case_case2.md":"CcpS4Un_","case_case3.md":"B7t7Pngt","case_case4.md":"Dvbv2ZQV","case_case5.md":"C0CClGSH","case_case6.md":"DvBOr9OH","case_case7.md":"C_6nm96W","case_index.md":"CTsnK0Eo","developer_index.md":"xDnRAGJI","developer_l10n.md":"Dmwl_ZMP","en_developer_index.md":"CxNmPWBh","en_developer_l10n.md":"BL9oMyMw","en_guide_block_block_docker.md":"BgbUSkc_","en_guide_block_block_incus.md":"BY8cyXbm","en_guide_block_block_iptables.md":"BjNGH3xq","en_guide_block_block_lxd.md":"Ivst4DHX","en_guide_block_block_pve.md":"DAY_vwpA","en_guide_dashboard.md":"2CtLmTVZ","en_guide_dashboardq.md":"8HU7kshN","en_guide_docker_docker_android.md":"BtLOd-bC","en_guide_docker_docker_build.md":"CL2XQyrX","en_guide_docker_docker_custom.md":"D5cECvek","en_guide_docker_docker_install.md":"Cidu0-4I","en_guide_docker_docker_macos.md":"lq2DVPwi","en_guide_docker_docker_precheck.md":"CcKlz8j3","en_guide_docker_docker_qa.md":"Db5w2l7v","en_guide_docker_docker_thanks.md":"CnuDwWda","en_guide_docker_docker_windows.md":"CPLcaNxO","en_guide_incus_incus_custom.md":"Ba2yzq78","en_guide_incus_incus_extra_config.md":"DH2SNY6K","en_guide_incus_incus_install.md":"CxedoQU0","en_guide_incus_incus_lxc.md":"VRGXWKjN","en_guide_incus_incus_precheck.md":"CnM0n_LH","en_guide_incus_incus_qa.md":"18NLI04c","en_guide_incus_incus_thanks.md":"Hpi2X21u","en_guide_incus_incus_windows.md":"CTYxF-Y8","en_guide_lxd_lxd_custom.md":"ChhF5aeL","en_guide_lxd_lxd_extra_config.md":"ClOBz_m4","en_guide_lxd_lxd_install.md":"c7FPeHrB","en_guide_lxd_lxd_lxc.md":"B3KW4VC4","en_guide_lxd_lxd_precheck.md":"DYFuiDkj","en_guide_lxd_lxd_qa.md":"ClKUkdaA","en_guide_lxd_lxd_thanks.md":"BQJJFjgN","en_guide_lxd_lxd_windows.md":"BezP75HS","en_guide_pve_images_readme.md":"BC6o0VpH","en_guide_pve_pve_android.md":"Dvi79OqQ","en_guide_pve_pve_custom.md":"B4Lc3Nfm","en_guide_pve_pve_install.md":"BJBHy5O6","en_guide_pve_pve_kvm.md":"9Dogwb6a","en_guide_pve_pve_lxc.md":"DMUp2OmO","en_guide_pve_pve_macos.md":"HWwGafcB","en_guide_pve_pve_precheck.md":"YWN-ymaX","en_guide_pve_pve_qa.md":"BNPMY08g","en_guide_pve_pve_thanks.md":"C6xQIo3i","en_guide_pve_pve_windows.md":"CCZ_Jnsi","en_incomplete_bashvm.md":"BdxLf4vW","en_incomplete_cockpit.md":"C0x03nL7","en_incomplete_convoy.md":"CsJ7T7KZ","en_incomplete_index.md":"Dc_QNlcS","en_incomplete_pterodactyl.md":"Dnnb38Pm","en_incomplete_virtfusion.md":"OOfZQV7R","en_incomplete_virtualizor-docker.md":"CIh0R0g2","en_incomplete_webvirtcloud.md":"N-ro4vUk","en_incomplete_webvirtcloud_retspen.md":"s6Zuv8G8","en_incomplete_webvirtmgr.md":"BjnPJDrR","en_index.md":"DAYXj-jV","guide_block_block_docker.md":"BJD9FRim","guide_block_block_incus.md":"3lsOzegp","guide_block_block_iptables.md":"Dc0xDmGo","guide_block_block_lxd.md":"D8Se-uK4","guide_block_block_pve.md":"BCj23GBU","guide_dashboard.md":"D8GQsHGi","guide_dashboardq.md":"DTEbLkzO","guide_docker_docker_android.md":"COugFG4U","guide_docker_docker_build.md":"DOq2-nhB","guide_docker_docker_custom.md":"CRxiuo2X","guide_docker_docker_install.md":"DIZm7xwQ","guide_docker_docker_macos.md":"DwHNXlgN","guide_docker_docker_precheck.md":"Dh4sv6Km","guide_docker_docker_qa.md":"BrZb-3sD","guide_docker_docker_thanks.md":"DTjt7pLo","guide_docker_docker_windows.md":"B5wj56qf","guide_incus_incus_custom.md":"BT3mJs2L","guide_incus_incus_extra_config.md":"CAisG7ZB","guide_incus_incus_install.md":"VMYGBkwe","guide_incus_incus_lxc.md":"C8ARsNcp","guide_incus_incus_precheck.md":"QhuGDOxQ","guide_incus_incus_qa.md":"BceKPQCa","guide_incus_incus_thanks.md":"-lO9ycIU","guide_incus_incus_windows.md":"CEsYWPV0","guide_lxd_lxd_custom.md":"DBDyje-Y","guide_lxd_lxd_extra_config.md":"DKAQT06a","guide_lxd_lxd_install.md":"NH49-6Z8","guide_lxd_lxd_lxc.md":"xiJ5_Hck","guide_lxd_lxd_precheck.md":"BaXVUfS1","guide_lxd_lxd_qa.md":"B5tdT2pN","guide_lxd_lxd_thanks.md":"C_fMTiRQ","guide_lxd_lxd_windows.md":"CSDQYWPt","guide_pve_images_readme.md":"Bb9hgKYp","guide_pve_pve_android.md":"BA0uMjS6","guide_pve_pve_custom.md":"DJmq2zf4","guide_pve_pve_install.md":"Bpv8rbx3","guide_pve_pve_kvm.md":"CUhjVf7a","guide_pve_pve_lxc.md":"V8cM-ZeN","guide_pve_pve_macos.md":"D5MpZ4_C","guide_pve_pve_precheck.md":"DtW8zi9R","guide_pve_pve_qa.md":"DxBmtnbo","guide_pve_pve_thanks.md":"BzrHp275","guide_pve_pve_windows.md":"CXNB_d7i","incomplete_bashvm.md":"D3-8bdef","incomplete_cockpit.md":"RVQdtVdP","incomplete_convoy.md":"D0MRT6x6","incomplete_index.md":"C8ULxG_M","incomplete_pterodactyl.md":"dbJsxVe0","incomplete_virtfusion.md":"CMqlkGCI","incomplete_virtualizor-docker.md":"Bg-O-Ud1","incomplete_webvirtcloud.md":"BHBm9zi3","incomplete_webvirtcloud_retspen.md":"CC1sOqkr","incomplete_webvirtmgr.md":"DK83_H_m","index.md":"C5KCCzHD"}
