{"en_guide_block_block_docker.md":"dd815174","en_guide_lxd_lxd_thanks.md":"e53cff25","en_guide_docker_docker_qa.md":"2f437b01","en_guide_incus_incus_precheck.md":"8ffb5221","en_guide_lxd_lxd_qa.md":"81028b06","en_guide_incus_incus_qa.md":"8df73101","case_case3.md":"53256f50","en_developer_index.md":"66f719a0","developer_l10n.md":"026414c9","case_case5.md":"18127213","en_guide_docker_docker_custom.md":"5d38bbb8","en_guide_docker_docker_install.md":"08f4b62c","en_guide_dashboardq.md":"0daf9231","en_guide_dashboard.md":"eefab26e","case_case4.md":"db65e09d","en_guide_block_block_pve.md":"49f82911","en_guide_pve_images_readme.md":"43c81bfb","en_guide_incus_incus_custom.md":"28b523c8","case_index.md":"db3f203c","developer_index.md":"35f95f46","en_developer_l10n.md":"a3c889ba","case_case2.md":"ae44d44b","en_guide_docker_docker_precheck.md":"f7540ade","en_guide_incus_incus_extra_config.md":"cec0335b","en_guide_block_block_lxd.md":"eec54a0e","en_guide_incus_incus_thanks.md":"22c1f663","en_guide_docker_docker_thanks.md":"c7285699","en_guide_pve_pve_android.md":"8d904175","case_case6.md":"8fa4418c","en_guide_pve_pve_custom.md":"dcd1dd5b","case_case7.md":"1bcc2379","en_guide_lxd_lxd_precheck.md":"a630c370","en_guide_incus_incus_install.md":"df396f7e","en_guide_docker_docker_build.md":"9f277404","case_case1.md":"40ae7a18","en_guide_lxd_lxd_install.md":"5eae7324","en_incomplete_virtualizor-docker.md":"84272a36","en_guide_incus_incus_lxc.md":"1d9d0b97","en_incomplete_convoy.md":"b9224eb7","en_incomplete_index.md":"36e92270","en_guide_lxd_lxd_lxc.md":"1a989308","en_incomplete_virtfusion.md":"eb40c153","en_guide_lxd_lxd_extra_config.md":"4caaf2cd","en_guide_block_block_iptables.md":"15f66073","en_incomplete_cockpit.md":"0e975099","en_incomplete_bashvm.md":"35c0ae91","en_guide_pve_pve_precheck.md":"d593d029","en_guide_pve_pve_qa.md":"32f02ca5","en_guide_pve_pve_thanks.md":"0a8e026b","en_guide_block_block_incus.md":"154f848a","en_guide_pve_pve_kvm.md":"0f2b494a","en_index.md":"ed3ce2da","en_incomplete_pterodactyl.md":"5c8944af","en_guide_lxd_lxd_custom.md":"f2f5b2cd","incomplete_bashvm.md":"d48a6852","incomplete_cockpit.md":"3031082c","incomplete_convoy.md":"a3b54622","incomplete_index.md":"040f404a","index.md":"3ba53309","incomplete_pterodactyl.md":"1cabe193","incomplete_virtfusion.md":"98cd5ecc","guide_docker_docker_qa.md":"d17442bf","incomplete_virtualizor-docker.md":"4978b87f","incomplete_webvirtcloud_retspen.md":"682d8d4c","en_guide_pve_pve_install.md":"f7fda4d3","incomplete_webvirtcloud.md":"df0c32db","incomplete_webvirtmgr.md":"3d681cfb","en_guide_pve_pve_macos.md":"ed02af9b","guide_docker_docker_windows.md":"6e51336e","guide_lxd_lxd_lxc.md":"8b27ee1b","guide_pve_pve_macos.md":"eb4fe12a","guide_pve_pve_precheck.md":"c0260093","guide_pve_pve_thanks.md":"745740ed","guide_pve_pve_qa.md":"ee6e8260","guide_pve_pve_windows.md":"7d8aef56","en_incomplete_webvirtcloud.md":"6aee9826","guide_block_block_lxd.md":"d0568f0e","guide_block_block_incus.md":"f0a6f6ce","guide_block_block_iptables.md":"b7d6814d","guide_block_block_docker.md":"b4818c55","en_incomplete_webvirtmgr.md":"ca446d37","guide_incus_incus_qa.md":"b919a2a3","guide_incus_incus_thanks.md":"f2fe7a58","guide_incus_incus_precheck.md":"13de0d3c","guide_docker_docker_android.md":"28a67d9d","guide_dashboardq.md":"2dcd957a","guide_incus_incus_lxc.md":"f44849f8","en_incomplete_webvirtcloud_retspen.md":"707b24ea","guide_pve_pve_android.md":"c7a53cb1","guide_incus_incus_install.md":"950fda8a","guide_pve_pve_install.md":"db2c628e","guide_pve_pve_lxc.md":"a161b937","guide_docker_docker_thanks.md":"adbc33d9","guide_lxd_lxd_extra_config.md":"af43c947","guide_pve_images_readme.md":"1823f547","guide_lxd_lxd_custom.md":"0f23b43b","en_guide_pve_pve_lxc.md":"a04185d4","guide_pve_pve_custom.md":"0277b8ef","guide_block_block_pve.md":"4f9c74c3","guide_dashboard.md":"c1165fc6","guide_docker_docker_install.md":"24b694dd","en_guide_pve_pve_windows.md":"a76e3792","guide_lxd_lxd_thanks.md":"d89b0b52","guide_lxd_lxd_qa.md":"6a84688e","guide_lxd_lxd_precheck.md":"80f1af9d","guide_docker_docker_build.md":"69fb42cb","guide_docker_docker_macos.md":"3890d2fd","guide_lxd_lxd_install.md":"3521feed","guide_docker_docker_precheck.md":"1defbd8d","guide_incus_incus_extra_config.md":"468732c3","guide_incus_incus_custom.md":"39c6ca59","guide_pve_pve_kvm.md":"a638276f","guide_docker_docker_custom.md":"bcf0a7d5"}
