{"case_case4.md":"5c724a26","case_case5.md":"8acf2098","case_case3.md":"d9c9be88","case_case6.md":"aa8326d0","en_guide_block_block_incus.md":"b197cb31","case_case7.md":"2301385c","case_case9.md":"4cd31dc8","case_index.md":"81cfb80b","en_developer_l10n.md":"d9395a22","en_guide_block_block_pve.md":"4656d7f6","en_guide_block_block_iptables.md":"7391adb6","case_case1.md":"b0cc92c3","developer_l10n.md":"dbf46cf6","en_guide_dashboard.md":"5f9c2a7c","en_guide_block_block_lxd.md":"523c1f63","en_developer_index.md":"b4533867","en_guide_docker_docker_install.md":"d6e6fdae","en_guide_docker_docker_precheck.md":"9575863c","en_guide_docker_docker_qa.md":"69a00c0f","en_guide_dashboardq.md":"30d2a719","en_guide_docker_docker_thanks.md":"8e1ebfc2","en_guide_block_block_docker.md":"72912c26","developer_index.md":"8cbee418","en_guide_docker_docker_build.md":"6fbe2b74","guide_block_block_docker.md":"fdb50045","guide_block_block_incus.md":"03e456b5","guide_incus_incus_thanks.md":"20888fd4","guide_docker_docker_thanks.md":"41d247ee","en_guide_pve_pve_precheck.md":"a9442e2e","en_guide_pve_pve_install.md":"75874136","en_guide_pve_pve_qa.md":"8e961c5c","guide_docker_docker_qa.md":"aff2b676","guide_lxd_lxd_qa.md":"3afe6aab","en_guide_pve_pve_thanks.md":"ba43b031","guide_pve_pve_lxc.md":"b56bb879","guide_incus_incus_extra_config.md":"9a51fa80","en_guide_pve_pve_lxc.md":"9ae24c76","en_guide_lxd_lxd_install.md":"4241d4ab","guide_lxd_lxd_thanks.md":"6e4446e5","en_guide_lxd_lxd_custom.md":"91a7db64","en_guide_pve_pve_custom.md":"17642c1a","en_guide_incus_incus_precheck.md":"ae018672","en_guide_incus_incus_install.md":"712fc823","en_guide_lxd_lxd_precheck.md":"8ef74515","guide_incus_incus_install.md":"29f1a5b8","guide_docker_docker_custom.md":"e30e09c0","en_index.md":"bf9a20d5","guide_lxd_lxd_install.md":"6cb40d1f","en_guide_incus_incus_extra_config.md":"3e5f3db3","en_guide_lxd_lxd_qa.md":"00ce6ddd","guide_incus_incus_precheck.md":"1b4e2fb0","guide_pve_pve_install.md":"59a37a85","en_guide_lxd_lxd_lxc.md":"ba66687f","guide_lxd_lxd_precheck.md":"c277eaca","guide_incus_incus_qa.md":"8c37dfc8","guide_incus_incus_lxc.md":"492f23e0","guide_lxd_lxd_lxc.md":"2c3693d8","en_guide_lxd_lxd_thanks.md":"3fbda666","guide_pve_pve_qa.md":"58448e43","guide_pve_pve_thanks.md":"ce81272b","en_guide_incus_incus_thanks.md":"f710ba17","index.md":"db60f42c","case_case2.md":"8f214eb8","guide_block_block_lxd.md":"48652fb8","guide_block_block_iptables.md":"7422b1b0","guide_block_block_pve.md":"a694a62e","guide_pve_pve_precheck.md":"b789a827","guide_lxd_lxd_extra_config.md":"f3bd3567","guide_incus_incus_custom.md":"17059f2b","case_case8.md":"a7c9c3e7","en_guide_incus_incus_lxc.md":"4639302a","en_guide_docker_docker_custom.md":"a01e1667","guide_dashboard.md":"bd023343","guide_docker_docker_precheck.md":"4fab72e8","guide_pve_pve_custom.md":"8e60094e","guide_pve_pve_kvm.md":"e1889175","en_guide_incus_incus_custom.md":"42e962ad","guide_dashboardq.md":"2b75dddc","en_guide_incus_incus_qa.md":"cdf3c0f0","en_guide_lxd_lxd_extra_config.md":"3d7c37a8","guide_docker_docker_build.md":"4218612e","guide_docker_docker_install.md":"4ce909ac","en_guide_pve_pve_kvm.md":"a3162928","guide_lxd_lxd_custom.md":"facfe2f0"}
