{"case_case2.md":"180b38cf","en_guide_docker_docker_build.md":"0ab1ac0a","en_guide_incus_incus_thanks.md":"8214d1fb","case_case8.md":"fbcbde4b","developer_index.md":"79529477","en_guide_incus_incus_precheck.md":"51debdf6","en_guide_incus_incus_lxc.md":"372e3efb","case_case3.md":"7a0ec629","en_guide_incus_incus_extra_config.md":"84d09720","en_guide_docker_docker_precheck.md":"7f091a2b","en_guide_lxd_lxd_custom.md":"3484139d","en_guide_incus_incus_custom.md":"fc9da0c4","en_guide_docker_docker_thanks.md":"6fe94f38","en_guide_docker_docker_custom.md":"2338b694","en_developer_l10n.md":"47532521","developer_l10n.md":"681685fb","case_index.md":"9b02c177","case_case5.md":"2d522b0c","en_guide_lxd_lxd_extra_config.md":"447998a6","case_case1.md":"d30382a9","case_case9.md":"e7278b43","case_case7.md":"fa298da2","en_guide_block_block_incus.md":"4e2f0800","en_guide_dashboardq.md":"306274b8","case_case6.md":"83a7a699","en_guide_incus_incus_install.md":"6a1f8478","en_guide_block_block_iptables.md":"f6b779e8","en_guide_dashboard.md":"cba2f772","en_developer_index.md":"66c3d26c","en_guide_incus_incus_qa.md":"aace6958","en_guide_block_block_docker.md":"d3219446","case_case4.md":"6bc6ee17","en_guide_block_block_lxd.md":"2b2832aa","en_guide_docker_docker_qa.md":"29079985","en_guide_docker_docker_install.md":"b17da960","en_guide_block_block_pve.md":"ebaf21d5","guide_block_block_lxd.md":"af7c4306","en_guide_pve_pve_thanks.md":"f05d7c8b","en_guide_pve_pve_install.md":"aecc4509","en_guide_pve_pve_precheck.md":"38441ea2","en_guide_pve_pve_custom.md":"54615a37","en_guide_lxd_lxd_thanks.md":"31d5ef58","guide_lxd_lxd_extra_config.md":"4031eec2","guide_lxd_lxd_install.md":"d075e953","guide_block_block_incus.md":"1e1a23b7","guide_docker_docker_custom.md":"b34dc6a3","en_guide_lxd_lxd_lxc.md":"111485f8","en_guide_lxd_lxd_precheck.md":"0e88e5d3","en_index.md":"a7488f7a","en_guide_lxd_lxd_install.md":"fce1708c","guide_dashboard.md":"0fc7be17","guide_incus_incus_qa.md":"793a4618","guide_lxd_lxd_lxc.md":"063f2b1b","en_guide_pve_pve_lxc.md":"8baaff9c","guide_incus_incus_precheck.md":"00bc52b2","guide_block_block_iptables.md":"1351d0ba","guide_lxd_lxd_precheck.md":"43067045","guide_dashboardq.md":"3aa635cb","guide_block_block_pve.md":"1e044438","guide_lxd_lxd_qa.md":"4abacacf","guide_lxd_lxd_thanks.md":"d7292706","guide_incus_incus_lxc.md":"2aa4dafd","guide_pve_pve_custom.md":"97e8f1ea","guide_docker_docker_install.md":"bc9c2b11","guide_incus_incus_install.md":"62d0ba71","guide_docker_docker_qa.md":"e4eec325","guide_docker_docker_thanks.md":"76242129","guide_docker_docker_precheck.md":"493ef18d","guide_pve_pve_precheck.md":"12c4312b","guide_pve_pve_kvm.md":"00c8fa29","guide_pve_pve_qa.md":"54f86baa","guide_pve_pve_thanks.md":"a975e450","index.md":"5909814d","guide_pve_pve_install.md":"4bb80d57","en_guide_pve_pve_kvm.md":"38a971b5","guide_block_block_docker.md":"8717353c","en_guide_pve_pve_qa.md":"feb3f12d","guide_lxd_lxd_custom.md":"4efa0ca1","guide_docker_docker_build.md":"fdb064d2","guide_incus_incus_thanks.md":"7814548d","guide_incus_incus_extra_config.md":"1d3d47ab","guide_incus_incus_custom.md":"9c44f011","guide_pve_pve_lxc.md":"6a7b826a","en_guide_lxd_lxd_qa.md":"8c57d23b"}
