{"case_case6.md":"a1d43b05","case_case1.md":"1efd5dc7","case_index.md":"f0d9aed3","case_case7.md":"c0ccc55e","developer_index.md":"f1f373b6","case_case3.md":"8293ccbb","en_guide_dashboard.md":"70f095cd","en_guide_dashboardq.md":"451ef3d3","case_case4.md":"d73febb6","case_case5.md":"737f158a","developer_l10n.md":"ead72b05","case_case9.md":"4c62dc60","case_case8.md":"a697c113","case_case2.md":"ddbd7763","en_guide_lxd_lxd_install.md":"c99399c6","guide_incus_incus_qa.md":"1d499a76","guide_incus_incus_precheck.md":"675277a1","en_guide_lxd_lxd_thanks.md":"dd3cf7af","en_guide_incus_incus_lxc.md":"d5b89f52","en_guide_docker_docker_precheck.md":"f154cf81","en_guide_docker_docker_thanks.md":"58d7c8bd","en_guide_docker_docker_qa.md":"975af133","en_developer_l10n.md":"06b2854b","en_developer_index.md":"c37d643c","en_guide_incus_incus_extra_config.md":"3fb8c6f0","en_guide_docker_docker_custom.md":"4545c0e8","en_guide_docker_docker_install.md":"ebf201c6","en_guide_pve_pve_custom.md":"e5ada7ad","en_guide_pve_pve_install.md":"ca191c89","en_guide_pve_pve_precheck.md":"5d0c9712","en_guide_pve_pve_lxc.md":"159a973e","guide_docker_docker_thanks.md":"19fc7a3a","guide_docker_docker_qa.md":"23175bf1","guide_incus_incus_extra_config.md":"afcc013d","en_guide_lxd_lxd_qa.md":"3a3db8a0","guide_incus_incus_custom.md":"05cc68c1","en_guide_docker_docker_build.md":"c0a1970f","guide_lxd_lxd_custom.md":"6d233e17","guide_incus_incus_lxc.md":"835a1aed","guide_lxd_lxd_install.md":"5c2d2ef2","guide_pve_pve_thanks.md":"8da71c43","guide_pve_pve_precheck.md":"18b73d8d","guide_pve_pve_qa.md":"dd1ccc20","index.md":"891be179","guide_pve_pve_kvm.md":"d09847ba","guide_pve_pve_lxc.md":"23922f65","en_guide_lxd_lxd_custom.md":"4e1e128e","en_guide_lxd_lxd_lxc.md":"cf84ec31","guide_incus_incus_install.md":"1bdca540","en_guide_incus_incus_install.md":"862fc918","en_guide_incus_incus_custom.md":"076d7ef6","en_guide_pve_pve_thanks.md":"a59d4afc","guide_docker_docker_precheck.md":"edc49191","en_index.md":"e71a63b4","guide_docker_docker_install.md":"c822a4f1","en_guide_pve_pve_qa.md":"e54bee1e","en_guide_pve_pve_kvm.md":"c6439674","guide_dashboardq.md":"fc953816","guide_docker_docker_custom.md":"2bca6ce2","guide_dashboard.md":"5281fb91","en_guide_incus_incus_qa.md":"fb802786","en_guide_incus_incus_precheck.md":"58abf3c3","guide_docker_docker_build.md":"4f51af92","guide_lxd_lxd_extra_config.md":"48b186fc","en_guide_lxd_lxd_precheck.md":"faaec600","en_guide_incus_incus_thanks.md":"0f9a6707","guide_lxd_lxd_precheck.md":"5565b67b","guide_pve_pve_install.md":"5f546455","guide_incus_incus_thanks.md":"aa316315","guide_lxd_lxd_thanks.md":"8872b160","guide_pve_pve_custom.md":"73f7af65","guide_lxd_lxd_qa.md":"9f89cdb5","guide_lxd_lxd_lxc.md":"c086aeb1","en_guide_lxd_lxd_extra_config.md":"45b560fb"}
