{"case_case1.md":"Bi5nPJn8","case_case2.md":"DVb0TUdO","case_case3.md":"DhKUKsLz","case_case4.md":"Au60V2xT","case_case5.md":"gr5RQvdh","case_case6.md":"D_yaEFE7","case_case7.md":"QK5CenDj","case_index.md":"Cye4OWVz","developer_index.md":"CejkODV-","developer_l10n.md":"CgyIY5lT","en_developer_index.md":"DzQSsEGf","en_developer_l10n.md":"DWivn4aY","en_guide_block_block_docker.md":"CV6byhUN","en_guide_block_block_incus.md":"ChlVw4Qr","en_guide_block_block_iptables.md":"BFyvS1Kb","en_guide_block_block_lxd.md":"ZkG1Ttj7","en_guide_block_block_pve.md":"yGxQe9wp","en_guide_containerd_containerd_build.md":"CpR1YMb9","en_guide_containerd_containerd_install.md":"zpSAdfv-","en_guide_containerd_containerd_precheck.md":"BZvV2RDB","en_guide_containerd_containerd_qa.md":"kujeZg3X","en_guide_containerd_containerd_thanks.md":"BRPGw36g","en_guide_dashboard.md":"GxRjgfbx","en_guide_dashboardq.md":"WmvJM5Kq","en_guide_docker_docker_android.md":"BJ0ohPV5","en_guide_docker_docker_build.md":"Dj-hQK4h","en_guide_docker_docker_custom.md":"CHIP0dyI","en_guide_docker_docker_install.md":"Ccwi1xbh","en_guide_docker_docker_macos.md":"Bm54widT","en_guide_docker_docker_precheck.md":"CbPLLLqm","en_guide_docker_docker_qa.md":"BgIKxPy2","en_guide_docker_docker_thanks.md":"CFxknrNF","en_guide_docker_docker_windows.md":"BZiGTxJh","en_guide_incus_incus_custom.md":"DYdxL254","en_guide_incus_incus_extra_config.md":"e2Gufx7d","en_guide_incus_incus_install.md":"BHSJsPT4","en_guide_incus_incus_lxc.md":"Dz1ti-O-","en_guide_incus_incus_precheck.md":"BTooLkAG","en_guide_incus_incus_qa.md":"DPTzihDf","en_guide_incus_incus_qemu.md":"DzpRyetI","en_guide_incus_incus_thanks.md":"JqGnItRE","en_guide_incus_incus_windows.md":"B_sN9OYY","en_guide_kubevirt_kubevirt_build.md":"Bq1FeOvD","en_guide_kubevirt_kubevirt_install.md":"CQglZhNN","en_guide_kubevirt_kubevirt_precheck.md":"DEVTJ98U","en_guide_kubevirt_kubevirt_qa.md":"C2ODvQhW","en_guide_kubevirt_kubevirt_thanks.md":"C0B6Z5n1","en_guide_lxd_lxd_custom.md":"DJjvntiN","en_guide_lxd_lxd_extra_config.md":"BL3ZxpHz","en_guide_lxd_lxd_install.md":"C8EAaa_g","en_guide_lxd_lxd_lxc.md":"COP46xfE","en_guide_lxd_lxd_precheck.md":"BWgkE6vm","en_guide_lxd_lxd_qa.md":"Be5RFczQ","en_guide_lxd_lxd_qemu.md":"DU-9Csm1","en_guide_lxd_lxd_thanks.md":"C9qOuEuG","en_guide_lxd_lxd_windows.md":"CRr-keiO","en_guide_oneclickvirt_oneclickvirt_install.md":"CiZMSo-l","en_guide_oneclickvirt_oneclickvirt_precheck.md":"CPjmEStV","en_guide_oneclickvirt_oneclickvirt_qa.md":"idK5uVvQ","en_guide_oneclickvirt_oneclickvirt_thanks.md":"CYOvIGkn","en_guide_oneclickvirt_oneclickvirt_usage.md":"Dui4gSQ1","en_guide_podman_podman_build.md":"V9Gipxgf","en_guide_podman_podman_install.md":"CRuMPeeb","en_guide_podman_podman_precheck.md":"BOnbJX6w","en_guide_podman_podman_qa.md":"C9Gf_cVr","en_guide_podman_podman_thanks.md":"BPI9o0sq","en_guide_pve_images_readme.md":"CHmqQ6BW","en_guide_pve_pve_android.md":"D5R2BW2l","en_guide_pve_pve_custom.md":"HTfX6Ecj","en_guide_pve_pve_install.md":"wxDsOY_g","en_guide_pve_pve_kvm.md":"BaeZjaAG","en_guide_pve_pve_lxc.md":"C-8fGylC","en_guide_pve_pve_macos.md":"CaBes3pU","en_guide_pve_pve_precheck.md":"Bi-q5Mpf","en_guide_pve_pve_qa.md":"B-stc4Xs","en_guide_pve_pve_thanks.md":"DFmRWzFy","en_guide_pve_pve_windows.md":"3oTPTh-A","en_guide_qemu_qemu_build.md":"Dst_0Ofa","en_guide_qemu_qemu_install.md":"nXG-_T9i","en_guide_qemu_qemu_precheck.md":"BK0PtTF0","en_guide_qemu_qemu_qa.md":"C_XAUFR9","en_guide_qemu_qemu_thanks.md":"BIgtKjvP","en_incomplete_bashvm.md":"C_rY1G3z","en_incomplete_cockpit.md":"DwuFDNW1","en_incomplete_convoy.md":"DJo7HZkm","en_incomplete_index.md":"2uagconH","en_incomplete_pterodactyl.md":"4CMjQEe9","en_incomplete_virtfusion.md":"DSaX9GDv","en_incomplete_virtualizor-docker.md":"JThR7KCz","en_incomplete_webvirtcloud.md":"BWVyey8H","en_incomplete_webvirtcloud_retspen.md":"ywBXAXRA","en_incomplete_webvirtmgr.md":"DXTrNSWV","en_index.md":"CjVJM_kK","guide_block_block_docker.md":"BgAMBTmH","guide_block_block_incus.md":"iTnRuuZF","guide_block_block_iptables.md":"BD2WOk36","guide_block_block_lxd.md":"BCOuZh4D","guide_block_block_pve.md":"DAfE-R2O","guide_containerd_containerd_build.md":"vZfXPzPv","guide_containerd_containerd_install.md":"Cmm3oRw9","guide_containerd_containerd_precheck.md":"BgUpYBIi","guide_containerd_containerd_qa.md":"CH3PXfG2","guide_containerd_containerd_thanks.md":"CI7CMRRK","guide_dashboard.md":"BHdHOPQf","guide_dashboardq.md":"DZSgNV9U","guide_docker_docker_android.md":"BVXy01iB","guide_docker_docker_build.md":"Br4eT_fJ","guide_docker_docker_custom.md":"BRsRZi_y","guide_docker_docker_install.md":"a38b6Lmx","guide_docker_docker_macos.md":"CLjJDj7r","guide_docker_docker_precheck.md":"D7ldM25f","guide_docker_docker_qa.md":"DSCASIKV","guide_docker_docker_thanks.md":"Cji4btTR","guide_docker_docker_windows.md":"wqvK9n4g","guide_incus_incus_custom.md":"Bv5x26rZ","guide_incus_incus_extra_config.md":"DyYYyva7","guide_incus_incus_install.md":"YKPnsgQn","guide_incus_incus_lxc.md":"EhqGSL5W","guide_incus_incus_precheck.md":"Dp2OsTzx","guide_incus_incus_qa.md":"D3j9CXW2","guide_incus_incus_qemu.md":"BRmKnwgm","guide_incus_incus_thanks.md":"BzSxLB0K","guide_incus_incus_windows.md":"sz4O05nt","guide_kubevirt_kubevirt_build.md":"B-aCHFUg","guide_kubevirt_kubevirt_install.md":"CDxQTGk6","guide_kubevirt_kubevirt_precheck.md":"CHw4LDus","guide_kubevirt_kubevirt_qa.md":"B49bQUyv","guide_kubevirt_kubevirt_thanks.md":"UntPwztN","guide_lxd_lxd_custom.md":"BArkcog7","guide_lxd_lxd_extra_config.md":"BcRAeYWK","guide_lxd_lxd_install.md":"mzdfqwFs","guide_lxd_lxd_lxc.md":"CoXwYwxV","guide_lxd_lxd_precheck.md":"DWa8QwYV","guide_lxd_lxd_qa.md":"D5Qr7q1r","guide_lxd_lxd_qemu.md":"CicOurST","guide_lxd_lxd_thanks.md":"B4R0hu7t","guide_lxd_lxd_windows.md":"CYUjcIW4","guide_oneclickvirt_oneclickvirt_install.md":"qLUPrQ4U","guide_oneclickvirt_oneclickvirt_precheck.md":"C3Dymmhu","guide_oneclickvirt_oneclickvirt_qa.md":"CQ4uEbi9","guide_oneclickvirt_oneclickvirt_thanks.md":"BjdzLhAB","guide_oneclickvirt_oneclickvirt_usage.md":"C35F3qlT","guide_podman_podman_build.md":"IjXxO4rj","guide_podman_podman_install.md":"gSl1yxkj","guide_podman_podman_precheck.md":"Dwq5UZ3g","guide_podman_podman_qa.md":"BGjAIlFG","guide_podman_podman_thanks.md":"H9bL7BWC","guide_pve_images_readme.md":"Fz269AWV","guide_pve_pve_android.md":"CkCtZ0bh","guide_pve_pve_custom.md":"CZry1zOJ","guide_pve_pve_install.md":"YK6ypyah","guide_pve_pve_kvm.md":"B9BmyvzH","guide_pve_pve_lxc.md":"DHhCQw8Y","guide_pve_pve_macos.md":"sR9ycsfk","guide_pve_pve_precheck.md":"Cv9x5dCX","guide_pve_pve_qa.md":"DL1JDPFI","guide_pve_pve_thanks.md":"BufV9hmw","guide_pve_pve_windows.md":"CdfKJLLd","guide_qemu_qemu_build.md":"Ck6V5Bdl","guide_qemu_qemu_install.md":"DWPXDSLo","guide_qemu_qemu_precheck.md":"CbbNeaZk","guide_qemu_qemu_qa.md":"BLXKRhcf","guide_qemu_qemu_thanks.md":"BN3hX6XM","incomplete_bashvm.md":"DiWipYn_","incomplete_cockpit.md":"DP0uN8Vo","incomplete_convoy.md":"DfX6KRRJ","incomplete_index.md":"Db01ww2O","incomplete_pterodactyl.md":"ByUsDUts","incomplete_virtfusion.md":"Ctsj4p9J","incomplete_virtualizor-docker.md":"C1eOEoK1","incomplete_webvirtcloud.md":"DrQACO60","incomplete_webvirtcloud_retspen.md":"gi9Oh-NN","incomplete_webvirtmgr.md":"CmoT4l1f","index.md":"MRRFg4QW"}
