{"case_case1.md":"Dl8lI6tL","case_case2.md":"CA1Wc6Yr","case_case3.md":"C4OKnJhe","case_case4.md":"KtWRKF2Z","case_case5.md":"ClSDR1ak","case_case6.md":"D47uMguH","case_case7.md":"oFa-7mr0","case_index.md":"fhCH1n2d","developer_index.md":"qDZQLV4e","developer_l10n.md":"DWa8qfxG","en_developer_index.md":"Bi-LlDLw","en_developer_l10n.md":"1c3HUt7q","en_guide_block_block_docker.md":"DcB6XMCD","en_guide_block_block_incus.md":"BDYFb6aA","en_guide_block_block_iptables.md":"DOw4dRxh","en_guide_block_block_lxd.md":"QZK4C_1X","en_guide_block_block_pve.md":"DTylJAMa","en_guide_dashboard.md":"BrLcUBZK","en_guide_dashboardq.md":"CJXSZhGI","en_guide_docker_docker_android.md":"Dbz0sbGi","en_guide_docker_docker_build.md":"DJQNHUf4","en_guide_docker_docker_custom.md":"3Dl_U5ls","en_guide_docker_docker_install.md":"DbIseDPS","en_guide_docker_docker_macos.md":"_5bhd8q8","en_guide_docker_docker_precheck.md":"CJtY3x8G","en_guide_docker_docker_qa.md":"DpqNzh4Q","en_guide_docker_docker_thanks.md":"BksgXSkz","en_guide_docker_docker_windows.md":"D60LBdbL","en_guide_incus_incus_custom.md":"CdTbDOsP","en_guide_incus_incus_extra_config.md":"BklwGjQF","en_guide_incus_incus_install.md":"B_tfzW0k","en_guide_incus_incus_lxc.md":"Co-8kaF-","en_guide_incus_incus_precheck.md":"D9lHAebo","en_guide_incus_incus_qa.md":"Dx1eVw6w","en_guide_incus_incus_thanks.md":"C9-p2rG_","en_guide_incus_incus_windows.md":"DJ6YoQVs","en_guide_lxd_lxd_custom.md":"BzwJmI6k","en_guide_lxd_lxd_extra_config.md":"Cqmzt17u","en_guide_lxd_lxd_install.md":"BBfl1NLe","en_guide_lxd_lxd_lxc.md":"DudrEa5U","en_guide_lxd_lxd_precheck.md":"Bsb8YJUn","en_guide_lxd_lxd_qa.md":"BHgO9xOm","en_guide_lxd_lxd_thanks.md":"CHOsJbCK","en_guide_lxd_lxd_windows.md":"qWvdGter","en_guide_pve_images_readme.md":"DMJiWE0j","en_guide_pve_pve_android.md":"BTKSUt6g","en_guide_pve_pve_custom.md":"CGorUxtI","en_guide_pve_pve_install.md":"DcJz8HAG","en_guide_pve_pve_kvm.md":"DZ1g9W20","en_guide_pve_pve_lxc.md":"CqFqc9bw","en_guide_pve_pve_macos.md":"CCB14gGO","en_guide_pve_pve_precheck.md":"Dpxx4VK_","en_guide_pve_pve_qa.md":"BSULqp49","en_guide_pve_pve_thanks.md":"BPMFjjM4","en_guide_pve_pve_windows.md":"CnEZYkC7","en_incomplete_bashvm.md":"YrDIctb-","en_incomplete_cockpit.md":"acl5NGHQ","en_incomplete_convoy.md":"Djr2kV4v","en_incomplete_index.md":"BSHN8S1L","en_incomplete_pterodactyl.md":"CbP9pgyh","en_incomplete_virtfusion.md":"DykeWjlT","en_incomplete_virtualizor-docker.md":"CX0DAcFq","en_incomplete_webvirtcloud.md":"C84egpi3","en_incomplete_webvirtcloud_retspen.md":"C0ak606G","en_incomplete_webvirtmgr.md":"BQrz0q0Q","en_index.md":"C26CSNK3","guide_block_block_docker.md":"Dz9BKU0k","guide_block_block_incus.md":"BWsoqJ4Y","guide_block_block_iptables.md":"D5JmB6Vl","guide_block_block_lxd.md":"CbV8zVRw","guide_block_block_pve.md":"BTJRyBrV","guide_dashboard.md":"PYqTYa3L","guide_dashboardq.md":"DsD2w-9Z","guide_docker_docker_android.md":"AY8eTWkL","guide_docker_docker_build.md":"DajvbW0i","guide_docker_docker_custom.md":"B6jaEINW","guide_docker_docker_install.md":"CV1TYCtv","guide_docker_docker_macos.md":"dwVhG6_t","guide_docker_docker_precheck.md":"C0L8kp9C","guide_docker_docker_qa.md":"Co7B-jsG","guide_docker_docker_thanks.md":"Cd7MGI_T","guide_docker_docker_windows.md":"D3n4yHE2","guide_incus_incus_custom.md":"BoFk6KML","guide_incus_incus_extra_config.md":"bK2q6AhF","guide_incus_incus_install.md":"D3PT1Xfk","guide_incus_incus_lxc.md":"BOBFLaGU","guide_incus_incus_precheck.md":"B2kJpnbR","guide_incus_incus_qa.md":"CW5GHmSm","guide_incus_incus_thanks.md":"m-Kwh0kq","guide_incus_incus_windows.md":"CK1uADyh","guide_lxd_lxd_custom.md":"CJgJuRzK","guide_lxd_lxd_extra_config.md":"DTiE2o4h","guide_lxd_lxd_install.md":"CMBWtSDW","guide_lxd_lxd_lxc.md":"DnOGrn-_","guide_lxd_lxd_precheck.md":"Cjhdp_fq","guide_lxd_lxd_qa.md":"B8aZC9BK","guide_lxd_lxd_thanks.md":"CzquJFpY","guide_lxd_lxd_windows.md":"CGv5qK2w","guide_pve_images_readme.md":"173ko8YO","guide_pve_pve_android.md":"DpZwmUDz","guide_pve_pve_custom.md":"to4X80LS","guide_pve_pve_install.md":"CXAmBkHg","guide_pve_pve_kvm.md":"D6a35qov","guide_pve_pve_lxc.md":"DW6W-clc","guide_pve_pve_macos.md":"DkjzX9BX","guide_pve_pve_precheck.md":"DqVKZop1","guide_pve_pve_qa.md":"BZDdpbc5","guide_pve_pve_thanks.md":"BxwUlJow","guide_pve_pve_windows.md":"BTj2mkQ-","incomplete_bashvm.md":"CA5P5n5t","incomplete_cockpit.md":"D4SqF2dO","incomplete_convoy.md":"-Sc-6ZCA","incomplete_index.md":"Q5NJBkkk","incomplete_pterodactyl.md":"BEgMY0JR","incomplete_virtfusion.md":"Ce_C7ghD","incomplete_virtualizor-docker.md":"DfGKovPP","incomplete_webvirtcloud.md":"ChOQdq8F","incomplete_webvirtcloud_retspen.md":"BcGQNMfF","incomplete_webvirtmgr.md":"4yvtchay","index.md":"CJq67ASU"}
