{"case_case2.md":"fad2c3b5","case_case5.md":"8e1aa795","en_us_guide_lxd_lxc.md":"0932cfca","en_us_guide_pve_install.md":"f3b92913","en_us_guide_dashboardq.md":"77920f8f","en_us_guide_docker_build.md":"36174051","en_us_guide_dashboard.md":"a867736d","en_us_guide_docker_custom.md":"5f4d582d","en_us_guide_docker_install.md":"5f077753","en_us_guide_docker_precheck.md":"94bb2cda","developer_index.md":"21cc4e09","en_us_guide_docker_thanks.md":"454fbe70","en_us_guide_lxd_custom.md":"bc0eb3e9","en_us_guide_lxd_extra_config.md":"de5ab589","en_us_guide_lxd_install.md":"be3218f3","en_us_guide_lxd_precheck.md":"e719ba03","en_us_guide_lxd_qa.md":"a41aad3b","en_us_guide_lxd_thanks.md":"8f1d1e7b","en_us_guide_pve_custom.md":"e245914b","guide_docker_custom.md":"6063a188","en_us_guide_docker_qa.md":"343d9312","guide_docker_install.md":"055b2020","case_index.md":"ae463d10","guide_docker_precheck.md":"356c7dbc","guide_docker_qa.md":"a4c25f62","en_us_developer_index.md":"b9aa1a9a","guide_docker_thanks.md":"f8f3d8fa","case_case4.md":"36c5fa8d","case_case3.md":"554bc6a9","guide_lxd_custom.md":"40806ab6","guide_lxd_install.md":"17b13c4c","guide_lxd_lxc.md":"f34dc233","guide_lxd_precheck.md":"11650ee2","guide_lxd_qa.md":"29a6005a","en_us_developer_l10n.md":"99b55b84","guide_lxd_thanks.md":"20d3b3fc","developer_l10n.md":"657deb49","guide_lxd_extra_config.md":"d8456550","guide_pve_thanks.md":"522af4e6","en_us_guide_pve_thanks.md":"d4630784","case_case6.md":"d11fcd51","guide_pve_install.md":"13e8a1a5","index.md":"b88030a4","en_us_guide_pve_lxc.md":"92b81bbd","en_us_guide_pve_precheck.md":"b9b6ef6b","en_us_index.md":"2ad0d1f8","guide_pve_kvm.md":"a9e4b7b4","en_us_guide_pve_kvm.md":"ee0f4537","case_case7.md":"428916cb","guide_pve_lxc.md":"1c53b32d","guide_dashboard.md":"be443928","guide_pve_qa.md":"773f12e6","case_case1.md":"6a683583","guide_docker_build.md":"42079492","guide_pve_custom.md":"4f2e8bea","en_us_guide_pve_qa.md":"e654a111","guide_pve_precheck.md":"b9e73c00","guide_dashboardq.md":"5ff6d0f8"}
