{"case_case1.md":"6c41817b","developer_index.md":"4b0c0870","case_case7.md":"a759cb24","case_case8.md":"7e009df4","en_guide_dashboard.md":"fc9178a1","en_guide_docker_docker_install.md":"8deb5a9c","en_guide_dashboardq.md":"5941b01b","en_guide_docker_docker_thanks.md":"33a86f71","en_guide_docker_docker_precheck.md":"19e0d080","developer_l10n.md":"56ec0058","case_case4.md":"dc6ac6c5","en_guide_docker_docker_custom.md":"08f1c257","case_case3.md":"bf60a05a","case_case5.md":"f52c0920","en_guide_incus_incus_install.md":"8cfacbc0","en_guide_lxd_lxd_qa.md":"dedd41d6","en_guide_lxd_lxd_precheck.md":"462e5fcd","en_guide_docker_docker_build.md":"cb339297","en_guide_lxd_lxd_install.md":"3b10db1c","en_guide_lxd_lxd_extra_config.md":"2d9e34d3","en_guide_lxd_lxd_lxc.md":"3404d9ec","en_guide_lxd_lxd_thanks.md":"ac095754","en_developer_l10n.md":"ab148f6f","case_index.md":"abdb7b1c","en_guide_incus_incus_precheck.md":"5f43e5a3","en_guide_pve_pve_thanks.md":"b6536189","en_index.md":"a7cdcfaf","guide_dashboard.md":"5830b628","guide_dashboardq.md":"0d726896","guide_docker_docker_custom.md":"a63a5bb5","guide_docker_docker_precheck.md":"f0fb4882","en_guide_docker_docker_qa.md":"accb5bcb","en_guide_incus_incus_custom.md":"18388bb6","guide_pve_pve_qa.md":"f52a00e8","case_case2.md":"8cbd29c9","index.md":"3ef9f01e","en_guide_lxd_lxd_custom.md":"38bbba94","guide_docker_docker_install.md":"3cec32de","guide_incus_incus_precheck.md":"0f25440e","guide_pve_pve_thanks.md":"2a3d3d5f","case_case9.md":"402cf712","en_guide_pve_pve_qa.md":"92ca9f50","en_guide_incus_incus_lxc.md":"dc2eee7f","guide_docker_docker_build.md":"3c5117c7","guide_docker_docker_qa.md":"2fd5946a","guide_pve_pve_lxc.md":"c6a192b8","guide_lxd_lxd_extra_config.md":"406ffd74","en_guide_incus_incus_extra_config.md":"0fba8f8c","guide_lxd_lxd_custom.md":"d8e559f1","guide_incus_incus_thanks.md":"cf5b804f","guide_lxd_lxd_lxc.md":"cf44d33b","case_case6.md":"e0b7aac8","en_guide_incus_incus_qa.md":"7c6c18fe","guide_lxd_lxd_precheck.md":"f1ec202b","en_guide_pve_pve_precheck.md":"91d2c5fb","en_guide_incus_incus_thanks.md":"70a8557a","en_developer_index.md":"f59f5a2c","guide_lxd_lxd_thanks.md":"47b909ec","guide_incus_incus_extra_config.md":"bcf46614","guide_docker_docker_thanks.md":"3b52585e","guide_lxd_lxd_install.md":"69fee5c5","en_guide_pve_pve_install.md":"b589e2a7","en_guide_pve_pve_kvm.md":"37d5fc84","guide_pve_pve_precheck.md":"f9ec99e5","guide_incus_incus_install.md":"bdd0b633","en_guide_pve_pve_custom.md":"d98d77c8","en_guide_pve_pve_lxc.md":"2f1abe26","guide_incus_incus_qa.md":"84663743","guide_lxd_lxd_qa.md":"91a6475c","guide_incus_incus_custom.md":"39b61430","guide_pve_pve_install.md":"5ee829bb","guide_pve_pve_custom.md":"d74b1fb7","guide_incus_incus_lxc.md":"32e72284","guide_pve_pve_kvm.md":"d402098c"}
