{"case_case1.md":"Cf6iCmtW","case_case2.md":"DegNulq9","case_case3.md":"Cvh0woW8","case_case4.md":"H1tAU7Fo","case_case5.md":"CeiKWGrz","case_case6.md":"Dl6M1YJT","case_case7.md":"DURMuK9Q","case_index.md":"0eStH5Oy","developer_index.md":"CMCEZ8U4","developer_l10n.md":"DMXK4YN3","en_developer_index.md":"BNtAEIt_","en_developer_l10n.md":"BftMkmrd","en_guide_block_block_docker.md":"aBZ66sTN","en_guide_block_block_incus.md":"DbGk2A9V","en_guide_block_block_iptables.md":"Dk8NWYGb","en_guide_block_block_lxd.md":"DPMS6lU8","en_guide_block_block_pve.md":"uzO7yMQp","en_guide_dashboard.md":"CZNYODHi","en_guide_dashboardq.md":"BpADMrRS","en_guide_docker_docker_android.md":"6rAdxiAl","en_guide_docker_docker_build.md":"DHZhOMlI","en_guide_docker_docker_custom.md":"WIXaJYAR","en_guide_docker_docker_install.md":"DKHxNp4e","en_guide_docker_docker_macos.md":"D9GND7V5","en_guide_docker_docker_precheck.md":"3_4sDJgh","en_guide_docker_docker_qa.md":"C1nof1JC","en_guide_docker_docker_thanks.md":"uq3y7n7g","en_guide_docker_docker_windows.md":"zsSiEKfC","en_guide_incus_incus_custom.md":"Bstz1S6F","en_guide_incus_incus_extra_config.md":"Dc06g6La","en_guide_incus_incus_install.md":"XLBeXmlO","en_guide_incus_incus_lxc.md":"DYVNwdun","en_guide_incus_incus_precheck.md":"CElUZxnP","en_guide_incus_incus_qa.md":"DiQKQqAi","en_guide_incus_incus_qemu.md":"BrICd7z3","en_guide_incus_incus_thanks.md":"Dnpig74D","en_guide_incus_incus_windows.md":"DqYBSfOL","en_guide_lxd_lxd_custom.md":"KzVELtxl","en_guide_lxd_lxd_extra_config.md":"BPzlGSHG","en_guide_lxd_lxd_install.md":"CHti_oIu","en_guide_lxd_lxd_lxc.md":"0WKbQux5","en_guide_lxd_lxd_precheck.md":"CNjFLpMB","en_guide_lxd_lxd_qa.md":"CjB5PWzR","en_guide_lxd_lxd_qemu.md":"DlKo5oGv","en_guide_lxd_lxd_thanks.md":"CwQHTCA1","en_guide_lxd_lxd_windows.md":"C98LZIMP","en_guide_oneclickvirt_oneclickvirt_install.md":"DUE7IpjA","en_guide_oneclickvirt_oneclickvirt_precheck.md":"DJCLOs3D","en_guide_oneclickvirt_oneclickvirt_qa.md":"CqyG3TKI","en_guide_oneclickvirt_oneclickvirt_thanks.md":"cb4E4Fg7","en_guide_oneclickvirt_oneclickvirt_usage.md":"D7BdXFaT","en_guide_pve_images_readme.md":"mJ7nrChY","en_guide_pve_pve_android.md":"CjERgPRU","en_guide_pve_pve_custom.md":"K1ddoYLX","en_guide_pve_pve_install.md":"CTS65ugp","en_guide_pve_pve_kvm.md":"DvQihzMO","en_guide_pve_pve_lxc.md":"Bjo1hSx7","en_guide_pve_pve_macos.md":"DzXZdo-J","en_guide_pve_pve_precheck.md":"szI0Ejus","en_guide_pve_pve_qa.md":"C8BWrZWj","en_guide_pve_pve_thanks.md":"J_d5Ib3u","en_guide_pve_pve_windows.md":"l1AYBOyK","en_incomplete_bashvm.md":"BihsduRU","en_incomplete_cockpit.md":"Denswswy","en_incomplete_convoy.md":"BWmadIgL","en_incomplete_index.md":"DW_2Gl69","en_incomplete_pterodactyl.md":"CF_cMKjN","en_incomplete_virtfusion.md":"OMLelr7g","en_incomplete_virtualizor-docker.md":"DTW22W1F","en_incomplete_webvirtcloud.md":"C4xg3xhf","en_incomplete_webvirtcloud_retspen.md":"C8UKo7Zx","en_incomplete_webvirtmgr.md":"x0T1Wc0p","en_index.md":"DjD5CIhW","guide_block_block_docker.md":"CVTHTu7s","guide_block_block_incus.md":"Bj-woY-i","guide_block_block_iptables.md":"3Lc5cOOJ","guide_block_block_lxd.md":"6S4nqf43","guide_block_block_pve.md":"zKpqhwJU","guide_dashboard.md":"DVKeU5He","guide_dashboardq.md":"84sIT0CY","guide_docker_docker_android.md":"DmjQkIKB","guide_docker_docker_build.md":"QTKVnQSJ","guide_docker_docker_custom.md":"BqdV-8O7","guide_docker_docker_install.md":"Czuw237J","guide_docker_docker_macos.md":"CZw2sbNZ","guide_docker_docker_precheck.md":"DRMxH2e7","guide_docker_docker_qa.md":"B3YEAGc3","guide_docker_docker_thanks.md":"Dm65hTGQ","guide_docker_docker_windows.md":"ChJS3yOM","guide_incus_incus_custom.md":"B6y7VYh7","guide_incus_incus_extra_config.md":"CQbogbfS","guide_incus_incus_install.md":"BNWp99Jd","guide_incus_incus_lxc.md":"DPSnFlbR","guide_incus_incus_precheck.md":"sYHcEjrv","guide_incus_incus_qa.md":"DIrlO7_0","guide_incus_incus_qemu.md":"CL_i9QhB","guide_incus_incus_thanks.md":"CnbYAvas","guide_incus_incus_windows.md":"B_Pp_MaT","guide_lxd_lxd_custom.md":"CeaEHdRN","guide_lxd_lxd_extra_config.md":"U1xOl6-f","guide_lxd_lxd_install.md":"r4gEIl8Y","guide_lxd_lxd_lxc.md":"C3gYW0yY","guide_lxd_lxd_precheck.md":"_LscUbko","guide_lxd_lxd_qa.md":"BeV8bn1m","guide_lxd_lxd_qemu.md":"B-YZtgRg","guide_lxd_lxd_thanks.md":"DTSsBRi0","guide_lxd_lxd_windows.md":"Dez7iOa3","guide_oneclickvirt_oneclickvirt_install.md":"Dm0ca0SW","guide_oneclickvirt_oneclickvirt_precheck.md":"CLKkQ5p6","guide_oneclickvirt_oneclickvirt_qa.md":"XFIr2Q1D","guide_oneclickvirt_oneclickvirt_thanks.md":"BJj55RXd","guide_oneclickvirt_oneclickvirt_usage.md":"Cd235-80","guide_pve_images_readme.md":"CbwSKGjF","guide_pve_pve_android.md":"R4A1nppw","guide_pve_pve_custom.md":"6LCIFN1F","guide_pve_pve_install.md":"pE339A0u","guide_pve_pve_kvm.md":"CoUzIAWm","guide_pve_pve_lxc.md":"Cw6rJ0DP","guide_pve_pve_macos.md":"B51n2KSW","guide_pve_pve_precheck.md":"sxSlsqEE","guide_pve_pve_qa.md":"BiGuOijb","guide_pve_pve_thanks.md":"GoPV1Oc0","guide_pve_pve_windows.md":"PjSlAyc6","incomplete_bashvm.md":"DhAnuapP","incomplete_cockpit.md":"BoGYX9UW","incomplete_convoy.md":"D84ULZXF","incomplete_index.md":"vLajCPO0","incomplete_pterodactyl.md":"D8aGtdr5","incomplete_virtfusion.md":"C10IwLjr","incomplete_virtualizor-docker.md":"6oWNNUD7","incomplete_webvirtcloud.md":"BLpXmMJJ","incomplete_webvirtcloud_retspen.md":"BA-vzknW","incomplete_webvirtmgr.md":"nVv8Y51x","index.md":"43eEYBO0"}
