{"en_guide_incus_incus_precheck.md":"60bd608d","en_guide_incus_incus_qa.md":"9f4b9914","en_guide_pve_pve_lxc.md":"fdf0a6b9","developer_l10n.md":"04e55f3d","en_developer_index.md":"6220c4d0","en_guide_docker_docker_custom.md":"9d5a45e3","en_guide_docker_docker_build.md":"711d1433","en_guide_docker_docker_precheck.md":"eae07848","en_guide_docker_docker_qa.md":"203a14e4","en_guide_dashboard.md":"49c38619","en_guide_dashboardq.md":"4e94970a","en_guide_docker_docker_thanks.md":"09cdddb9","en_guide_docker_docker_install.md":"ae7a0414","en_guide_incus_incus_install.md":"dc71e577","en_guide_incus_incus_extra_config.md":"6d5a1c29","case_case2.md":"ea3ec659","case_case7.md":"071fa02d","case_index.md":"427155dd","en_guide_incus_incus_lxc.md":"b555c44b","en_guide_pve_pve_custom.md":"fda46d8a","en_guide_lxd_lxd_thanks.md":"3a7deaca","case_case1.md":"d852f21d","en_guide_pve_pve_precheck.md":"697ddf7d","en_guide_lxd_lxd_lxc.md":"638ea1a3","en_guide_pve_pve_qa.md":"c2389d39","en_guide_lxd_lxd_install.md":"86521b6e","en_index.md":"51bb89d6","en_guide_pve_pve_thanks.md":"caeb35ee","guide_dashboard.md":"cc79f91c","guide_dashboardq.md":"851a875f","guide_docker_docker_build.md":"273ce28a","guide_docker_docker_precheck.md":"88e68c32","guide_docker_docker_custom.md":"6115d9ff","guide_docker_docker_install.md":"84346e15","guide_lxd_lxd_precheck.md":"9a39e2ca","guide_incus_incus_extra_config.md":"012dcb9c","guide_incus_incus_custom.md":"7dbf72c3","guide_incus_incus_qa.md":"a157031b","guide_incus_incus_precheck.md":"98cb526f","guide_incus_incus_install.md":"32466781","guide_lxd_lxd_thanks.md":"89e29a89","guide_lxd_lxd_qa.md":"5fff8cde","guide_pve_pve_install.md":"cebecaf1","guide_pve_pve_custom.md":"599b0a50","guide_pve_pve_precheck.md":"008774e3","guide_pve_pve_thanks.md":"23e739da","index.md":"8deb5b69","guide_pve_pve_qa.md":"09aa6911","en_guide_lxd_lxd_precheck.md":"91057a0d","en_guide_pve_pve_install.md":"26062028","en_guide_incus_incus_thanks.md":"95c4ac9a","en_guide_lxd_lxd_qa.md":"709995c6","guide_docker_docker_qa.md":"d8485d2a","en_guide_incus_incus_custom.md":"5ea83552","guide_docker_docker_thanks.md":"47aaa9ee","en_developer_l10n.md":"eb1c25f8","case_case4.md":"ac7a6b75","guide_incus_incus_thanks.md":"cb376794","developer_index.md":"e1147f16","en_guide_pve_pve_kvm.md":"bd559963","case_case5.md":"23de121e","guide_incus_incus_lxc.md":"eb717bf1","guide_lxd_lxd_custom.md":"20c9fd47","guide_lxd_lxd_install.md":"2c1f6e6a","en_guide_lxd_lxd_custom.md":"ece63d32","case_case6.md":"6beeaeb6","case_case3.md":"b267af51","guide_pve_pve_lxc.md":"43e59225","guide_pve_pve_kvm.md":"a6350460","en_guide_lxd_lxd_extra_config.md":"8b04167f","guide_lxd_lxd_extra_config.md":"d4a98de6","guide_lxd_lxd_lxc.md":"d6b2a341"}
