{"case_case1.md":"1f52aeaf","case_case3.md":"f9cc625f","case_case4.md":"496244a2","case_case5.md":"edcb16df","case_index.md":"b8aaa09a","developer_index.md":"9c764237","case_case2.md":"2a1d63f8","developer_l10n.md":"cbf4db0b","en_us_guide_dashboard.md":"6fd911cd","en_us_guide_dashboardq.md":"ec7c96c5","en_us_guide_docker_build.md":"f0c51bc0","en_us_guide_docker_install.md":"b865595b","en_us_guide_docker_precheck.md":"24a47164","en_us_guide_docker_qa.md":"dea95472","en_us_guide_docker_thanks.md":"54832a56","en_us_guide_lxd_extra_config.md":"6ef7f6b9","en_us_developer_index.md":"c0cb3c0b","en_us_guide_lxd_install.md":"7a941496","en_us_guide_lxd_lxc.md":"e30dced7","en_us_guide_lxd_precheck.md":"5905421d","en_us_guide_lxd_qa.md":"74d3e2b0","en_us_guide_pve_precheck.md":"3bd138e0","en_us_guide_lxd_thanks.md":"5f9e8b92","en_us_guide_pve_thanks.md":"51321879","en_us_index.md":"01d2cfcc","en_us_guide_pve_lxc.md":"bf278da8","en_us_guide_pve_kvm.md":"e76b6c3f","en_us_guide_pve_qa.md":"f07a2d37","guide_dashboardq.md":"1f4c9eb4","guide_docker_build.md":"8b1b00cf","guide_docker_thanks.md":"2156bf52","guide_docker_install.md":"3688c5e7","guide_lxd_install.md":"ac6005ae","guide_docker_precheck.md":"f1cde707","guide_docker_qa.md":"1f2dfc35","guide_lxd_extra_config.md":"82bc9273","guide_pve_kvm.md":"d4b38fd2","guide_pve_install.md":"ca123f4c","en_us_developer_l10n.md":"093d582c","guide_pve_qa.md":"737460e0","guide_lxd_lxc.md":"7192053c","guide_lxd_precheck.md":"ad95e089","guide_lxd_thanks.md":"c2eeefce","guide_pve_lxc.md":"ced1dd96","guide_pve_precheck.md":"368c299d","index.md":"e2653ac2","guide_lxd_qa.md":"daab254d","en_us_guide_pve_install.md":"7087d1e8","guide_dashboard.md":"96c793ca","guide_pve_thanks.md":"189c9b8c"}
