{"case_case7.md":"a0df0781","developer_index.md":"9b4374fb","en_guide_docker_docker_install.md":"6f61a6ee","en_guide_docker_docker_precheck.md":"880fd40d","en_developer_l10n.md":"6fcdb680","case_case2.md":"0bba89ae","case_index.md":"64cb4893","en_guide_dashboardq.md":"0cac4604","en_developer_index.md":"6cfe0d49","case_case4.md":"05f306ce","en_guide_block_block_docker.md":"67ff6cc8","case_case6.md":"bdab9a2f","en_guide_block_block_pve.md":"c84e1f20","case_case3.md":"6b32b96f","en_guide_docker_docker_qa.md":"a408696f","developer_l10n.md":"cef8eafd","case_case8.md":"7ded98a0","en_guide_docker_docker_thanks.md":"0bcbf01b","case_case5.md":"1ece8cd4","en_guide_docker_docker_custom.md":"e0de4cfa","en_guide_block_block_lxd.md":"fd227ba1","en_guide_block_block_incus.md":"ef0b32ba","case_case1.md":"2851bbd6","en_guide_block_block_iptables.md":"d3be068b","en_incomplete_pterodactyl.md":"7aa00c43","en_incomplete_index.md":"26d25fbc","en_guide_docker_docker_build.md":"54343577","guide_incus_incus_extra_config.md":"12d8e588","en_guide_lxd_lxd_install.md":"4cd08436","en_incomplete_webvirtcloud.md":"0dfe6ee0","guide_dashboard.md":"0643bbde","guide_incus_incus_lxc.md":"19c77896","guide_block_block_pve.md":"f827bf8d","guide_lxd_lxd_precheck.md":"f9908f08","en_guide_incus_incus_install.md":"40c504c8","guide_block_block_lxd.md":"4b3de125","guide_dashboardq.md":"2f733490","en_guide_lxd_lxd_extra_config.md":"ce1a20cd","en_guide_dashboard.md":"221b5727","guide_incus_incus_install.md":"957a8ece","guide_block_block_incus.md":"486642cf","en_guide_pve_pve_kvm.md":"55a18c96","en_guide_incus_incus_lxc.md":"add7810d","en_guide_pve_pve_thanks.md":"88471534","guide_block_block_iptables.md":"fd61e9c6","en_guide_pve_pve_windows.md":"17dc07c4","guide_lxd_lxd_qa.md":"e3604599","en_guide_pve_pve_install.md":"f64232f5","guide_docker_docker_build.md":"c39849c2","guide_pve_images_readme.md":"ca82511e","guide_docker_docker_install.md":"acb3c1ff","guide_block_block_docker.md":"248ffc88","en_guide_incus_incus_custom.md":"c98ba1a7","guide_pve_pve_custom.md":"9e0175aa","guide_docker_docker_qa.md":"554874a8","guide_lxd_lxd_install.md":"b841b975","en_guide_lxd_lxd_precheck.md":"875ca10c","guide_lxd_lxd_thanks.md":"d6962453","guide_pve_pve_windows.md":"d0ecb9d1","en_guide_lxd_lxd_qa.md":"6e0f9f20","en_guide_incus_incus_qa.md":"b759a715","en_guide_incus_incus_thanks.md":"d03f028e","en_incomplete_convoy.md":"9fada117","guide_pve_pve_lxc.md":"ce51f675","en_guide_pve_pve_qa.md":"ad782929","en_guide_pve_pve_lxc.md":"d30c366e","en_guide_lxd_lxd_thanks.md":"dd725c4c","guide_lxd_lxd_lxc.md":"c9379249","guide_pve_pve_thanks.md":"e906d9b5","guide_pve_pve_qa.md":"bb4c117d","en_guide_pve_images_readme.md":"d327d75e","en_guide_lxd_lxd_lxc.md":"912fd0c7","guide_docker_docker_thanks.md":"27cfdda7","en_guide_incus_incus_extra_config.md":"f062147e","en_guide_incus_incus_precheck.md":"5f01fdb8","guide_docker_docker_custom.md":"7ed669ef","en_guide_lxd_lxd_custom.md":"8ac6b656","guide_incus_incus_qa.md":"8684d1b4","guide_docker_docker_precheck.md":"7e00b6b2","incomplete_webvirtcloud.md":"681033c4","guide_lxd_lxd_extra_config.md":"1d300e11","guide_incus_incus_precheck.md":"2e793eac","en_index.md":"1b595508","incomplete_index.md":"f2c9749e","en_guide_pve_pve_custom.md":"280bd025","guide_pve_pve_kvm.md":"98726084","guide_incus_incus_thanks.md":"2bb28c4d","incomplete_pterodactyl.md":"a9c1503e","index.md":"eb4c9074","incomplete_convoy.md":"afe2da0b","guide_pve_pve_install.md":"10631719","guide_pve_pve_precheck.md":"d4c743fe","guide_lxd_lxd_custom.md":"43111866","en_guide_pve_pve_precheck.md":"680b14c3","guide_incus_incus_custom.md":"220f2973"}
