{"en_us_guide_pve_custom.md":"3acfd11b","en_us_guide_docker_build.md":"af8a78c6","en_us_guide_docker_custom.md":"3b250a56","en_us_guide_docker_install.md":"bcd08410","guide_lxd_lxc.md":"df15cfda","en_us_guide_pve_install.md":"81443499","en_us_guide_pve_kvm.md":"12e9ba7d","en_us_guide_pve_lxc.md":"994f3dfc","en_us_guide_pve_precheck.md":"b4617fe6","en_us_guide_docker_qa.md":"3c8f3a01","en_us_guide_pve_thanks.md":"90cdf4f8","en_us_index.md":"b941f2b0","en_us_guide_docker_thanks.md":"b07448bf","guide_dashboardq.md":"f0085977","guide_docker_build.md":"df6d21ef","guide_docker_custom.md":"ab72b0af","guide_docker_install.md":"e3ba04fc","guide_docker_precheck.md":"fd7940b2","guide_docker_qa.md":"bb0181a0","guide_lxd_custom.md":"d95a6853","guide_lxd_extra_config.md":"45239554","guide_lxd_install.md":"3d526feb","guide_lxd_precheck.md":"70741617","guide_pve_custom.md":"1f657201","guide_pve_kvm.md":"40f8a061","guide_pve_qa.md":"e63546f3","guide_pve_thanks.md":"0a3647fc","index.md":"a0535a91","en_us_guide_lxd_thanks.md":"18bcae4f","guide_dashboard.md":"46b96e9d","guide_docker_thanks.md":"d4478d34","en_us_guide_dashboard.md":"7032cb49","en_us_guide_lxd_custom.md":"1fa257bf","en_us_guide_lxd_install.md":"21f7cb23","en_us_guide_lxd_qa.md":"7829bcf4","en_us_guide_lxd_lxc.md":"02e5cd8f","case_case3.md":"319639a0","en_us_guide_dashboardq.md":"73a423c8","en_us_guide_lxd_extra_config.md":"ef9d8cb3","en_us_guide_docker_precheck.md":"f7da6712","guide_lxd_qa.md":"d6d31e31","case_case1.md":"b77890fd","case_case4.md":"d6043483","case_index.md":"b95ae9db","guide_pve_lxc.md":"7fefec55","en_us_guide_lxd_precheck.md":"2640d205","developer_l10n.md":"fd00e37e","case_case2.md":"7fff15dc","case_case5.md":"bbf0846c","guide_lxd_thanks.md":"4d982f95","en_us_guide_pve_qa.md":"614bc04d","developer_index.md":"e6cad3e6","en_us_developer_index.md":"49632897","en_us_developer_l10n.md":"95de0b52","guide_pve_install.md":"61201881","guide_pve_precheck.md":"5689c014"}
