{"en_us_guide_lxd_qa.md":"87249493","en_us_guide_lxd_thanks.md":"f7fef3dc","en_us_guide_pve_install.md":"519ceee1","en_us_guide_pve_kvm.md":"0c1912b8","en_us_guide_pve_lxc.md":"6c7545ad","en_us_guide_pve_precheck.md":"851e703d","en_us_guide_pve_qa.md":"5bec54d5","en_us_guide_pve_thanks.md":"2d8800fe","en_us_index.md":"30f05716","en_us_guide_lxd_lxc.md":"7ebf5e56","guide_dashboard.md":"6fff820f","guide_dashboardq.md":"8f06647b","en_us_guide_lxd_precheck.md":"8049b9ea","guide_docker_build.md":"a774c35c","guide_docker_qa.md":"bd402d40","guide_lxd_install.md":"f399ad36","guide_docker_precheck.md":"ff817415","guide_lxd_qa.md":"c78062b6","guide_lxd_thanks.md":"c6349dc7","guide_lxd_extra_config.md":"fc6c89d0","guide_docker_thanks.md":"fba6d0e2","guide_pve_lxc.md":"8e633684","guide_docker_install.md":"204cba92","guide_lxd_lxc.md":"0d2f2b59","developer_index.md":"a0a48e68","guide_pve_precheck.md":"6a5928ae","guide_lxd_precheck.md":"3352b0d1","guide_pve_install.md":"6580fedd","en_us_guide_docker_install.md":"c06b9610","guide_pve_kvm.md":"3bbeeb56","en_us_guide_docker_precheck.md":"64ecc14d","case_case3.md":"387aa1cd","guide_pve_thanks.md":"db6d9dc2","en_us_guide_docker_build.md":"fe188475","case_case2.md":"632e3026","case_case4.md":"00e107cd","case_case5.md":"aa2ab88d","en_us_guide_dashboard.md":"bba534bf","guide_pve_qa.md":"768b8be2","case_case1.md":"2ddeb098","en_us_guide_docker_thanks.md":"514a2a2b","en_us_guide_dashboardq.md":"5ee3824b","case_index.md":"45094b4e","developer_l10n.md":"9e7df734","en_us_developer_index.md":"519c5fd0","index.md":"99fb9479","en_us_guide_docker_qa.md":"927fc6e6","en_us_guide_lxd_extra_config.md":"c90216da","en_us_developer_l10n.md":"0510467d","en_us_guide_lxd_install.md":"bae37369"}
