{"case_case1.md":"B_L677aD","case_case2.md":"Bi2RYIdT","case_case3.md":"BvrVU5SJ","case_case4.md":"4Hf1xsK2","case_case5.md":"UbZQYOkk","case_case6.md":"C5orQXMk","case_case7.md":"agWU4t_A","case_index.md":"D4MQty_c","developer_index.md":"r3kwPi_t","developer_l10n.md":"G35yAdba","en_developer_index.md":"CR5JSB6R","en_developer_l10n.md":"CspEyVLR","en_guide_block_block_docker.md":"BcUATIGh","en_guide_block_block_incus.md":"wjJR3ro3","en_guide_block_block_iptables.md":"CQh9FfY4","en_guide_block_block_lxd.md":"DXvdC2Cg","en_guide_block_block_pve.md":"0KCUf4KK","en_guide_containerd_containerd_build.md":"DdPaINrC","en_guide_containerd_containerd_install.md":"DGtKJnx8","en_guide_containerd_containerd_precheck.md":"ClTA4zal","en_guide_containerd_containerd_qa.md":"BHimqcWr","en_guide_containerd_containerd_thanks.md":"Bz27py1Y","en_guide_dashboard.md":"COXDfcrB","en_guide_dashboardq.md":"D4VkqjRF","en_guide_docker_docker_android.md":"D36suc1j","en_guide_docker_docker_build.md":"4AU7pDL9","en_guide_docker_docker_custom.md":"CW9sFVv_","en_guide_docker_docker_install.md":"yeDlAOS5","en_guide_docker_docker_macos.md":"B-27DPbM","en_guide_docker_docker_precheck.md":"_chG0wUt","en_guide_docker_docker_qa.md":"974S2wwI","en_guide_docker_docker_thanks.md":"Cn6VZq0S","en_guide_docker_docker_windows.md":"3PfgRvse","en_guide_incus_incus_custom.md":"CsWNjjxG","en_guide_incus_incus_extra_config.md":"Dr1qTPcl","en_guide_incus_incus_install.md":"hdIbk1po","en_guide_incus_incus_lxc.md":"_bTip1Ub","en_guide_incus_incus_precheck.md":"DBBM44YS","en_guide_incus_incus_qa.md":"GseGoNjL","en_guide_incus_incus_qemu.md":"BgVQYDz-","en_guide_incus_incus_thanks.md":"BOhT9kDv","en_guide_incus_incus_windows.md":"CB-MXhl2","en_guide_lxd_lxd_custom.md":"BuoYFyrL","en_guide_lxd_lxd_extra_config.md":"DilF79sp","en_guide_lxd_lxd_install.md":"Dm-AP6iw","en_guide_lxd_lxd_lxc.md":"Df4IkzL_","en_guide_lxd_lxd_precheck.md":"FBOBo4eE","en_guide_lxd_lxd_qa.md":"CoAwiIE5","en_guide_lxd_lxd_qemu.md":"CWB-pXl7","en_guide_lxd_lxd_thanks.md":"DZe-0H6X","en_guide_lxd_lxd_windows.md":"D7f4OoQI","en_guide_oneclickvirt_oneclickvirt_install.md":"CpP4Nxv_","en_guide_oneclickvirt_oneclickvirt_precheck.md":"CTP4Q8vT","en_guide_oneclickvirt_oneclickvirt_qa.md":"Dq5O4kXg","en_guide_oneclickvirt_oneclickvirt_thanks.md":"DfA7zu-W","en_guide_oneclickvirt_oneclickvirt_usage.md":"CSQ0IE81","en_guide_podman_podman_build.md":"BStFWgWW","en_guide_podman_podman_install.md":"Lkx1-Z0c","en_guide_podman_podman_precheck.md":"BLEI_OBX","en_guide_podman_podman_qa.md":"Ccq4IBpf","en_guide_podman_podman_thanks.md":"Czg7rcqs","en_guide_pve_images_readme.md":"CdhBxXXN","en_guide_pve_pve_android.md":"ChwUrQct","en_guide_pve_pve_custom.md":"CQtl_dNW","en_guide_pve_pve_install.md":"B28IFOVT","en_guide_pve_pve_kvm.md":"EedGwoAp","en_guide_pve_pve_lxc.md":"A4xPAQIV","en_guide_pve_pve_macos.md":"C-ydY8bK","en_guide_pve_pve_precheck.md":"ctexfw-q","en_guide_pve_pve_qa.md":"DgIBo7yj","en_guide_pve_pve_thanks.md":"y42sMaye","en_guide_pve_pve_windows.md":"BnnPOUCS","en_incomplete_bashvm.md":"7tk-ZEu5","en_incomplete_cockpit.md":"aU_2U-XH","en_incomplete_convoy.md":"BnLEXvtr","en_incomplete_index.md":"CMWZwnav","en_incomplete_pterodactyl.md":"DuCiAjw4","en_incomplete_virtfusion.md":"7zslYcjH","en_incomplete_virtualizor-docker.md":"CYmV5ays","en_incomplete_webvirtcloud.md":"6vLBPYN0","en_incomplete_webvirtcloud_retspen.md":"NfY8LdF5","en_incomplete_webvirtmgr.md":"DdlBuLO9","en_index.md":"BrEPoFob","guide_block_block_docker.md":"Ch6FJWSI","guide_block_block_incus.md":"DrzhoJQy","guide_block_block_iptables.md":"Dx4FHQiC","guide_block_block_lxd.md":"bAOyt_Yn","guide_block_block_pve.md":"D9jjCIrc","guide_containerd_containerd_build.md":"DeyNG5NW","guide_containerd_containerd_install.md":"DpBuC67s","guide_containerd_containerd_precheck.md":"DQrDdUYj","guide_containerd_containerd_qa.md":"DweiiNoU","guide_containerd_containerd_thanks.md":"B8ocld4Z","guide_dashboard.md":"5DkCRi2q","guide_dashboardq.md":"Dywt66cz","guide_docker_docker_android.md":"DaSSuPZa","guide_docker_docker_build.md":"Bqjx65p4","guide_docker_docker_custom.md":"MBT0wSpc","guide_docker_docker_install.md":"BLH4X-Np","guide_docker_docker_macos.md":"H8XECkrb","guide_docker_docker_precheck.md":"FwVDrBjS","guide_docker_docker_qa.md":"B8nIoB11","guide_docker_docker_thanks.md":"BRma5Ogy","guide_docker_docker_windows.md":"CyUC6-x6","guide_incus_incus_custom.md":"CwQ9DXPv","guide_incus_incus_extra_config.md":"CJzw0Jvq","guide_incus_incus_install.md":"Dzu8xto4","guide_incus_incus_lxc.md":"B9bz-wqX","guide_incus_incus_precheck.md":"B7EicS4v","guide_incus_incus_qa.md":"CQnLz1cg","guide_incus_incus_qemu.md":"DEvirL6X","guide_incus_incus_thanks.md":"D1W1P5MD","guide_incus_incus_windows.md":"DDdBCbEm","guide_lxd_lxd_custom.md":"D7SlIu6J","guide_lxd_lxd_extra_config.md":"BUIC4UCD","guide_lxd_lxd_install.md":"lF46ja40","guide_lxd_lxd_lxc.md":"3TiBQZB0","guide_lxd_lxd_precheck.md":"CWp5sTOR","guide_lxd_lxd_qa.md":"457JFcFy","guide_lxd_lxd_qemu.md":"BNQDW1qK","guide_lxd_lxd_thanks.md":"BuXAtsXG","guide_lxd_lxd_windows.md":"BU1xap_h","guide_oneclickvirt_oneclickvirt_install.md":"DvvKispM","guide_oneclickvirt_oneclickvirt_precheck.md":"RfnnTBIh","guide_oneclickvirt_oneclickvirt_qa.md":"0XSO40vD","guide_oneclickvirt_oneclickvirt_thanks.md":"C42YDVKE","guide_oneclickvirt_oneclickvirt_usage.md":"8MvNCVKk","guide_podman_podman_build.md":"Ca6jlQVY","guide_podman_podman_install.md":"BmGKzJEO","guide_podman_podman_precheck.md":"Cyl5FMaw","guide_podman_podman_qa.md":"CpNEmPSh","guide_podman_podman_thanks.md":"BIq_rBaL","guide_pve_images_readme.md":"DzT8DeZh","guide_pve_pve_android.md":"BYa7TTTG","guide_pve_pve_custom.md":"DIveMndF","guide_pve_pve_install.md":"DMVLl-nh","guide_pve_pve_kvm.md":"B2IGxG-S","guide_pve_pve_lxc.md":"BSeih7FS","guide_pve_pve_macos.md":"BKxiSjd3","guide_pve_pve_precheck.md":"BzrRoC6D","guide_pve_pve_qa.md":"Cb_sHsYT","guide_pve_pve_thanks.md":"OEVM-z7H","guide_pve_pve_windows.md":"CgcOlWEK","incomplete_bashvm.md":"ulBcWfGK","incomplete_cockpit.md":"BJoO4w05","incomplete_convoy.md":"7Wc1m7po","incomplete_index.md":"DLyUERmz","incomplete_pterodactyl.md":"DJBeL-tc","incomplete_virtfusion.md":"QYJAyYWd","incomplete_virtualizor-docker.md":"BjoBN8Nn","incomplete_webvirtcloud.md":"Ce7iEahO","incomplete_webvirtcloud_retspen.md":"yiTxty3Z","incomplete_webvirtmgr.md":"XecR36zI","index.md":"Cfr7VjVV"}
