{"en_us_guide_docker_qa.md":"0516b7b3","guide_docker_thanks.md":"bf1cff34","en_us_guide_pve_lxc.md":"59c1751f","guide_lxd_extra_config.md":"861a551a","en_us_developer_l10n.md":"8139a943","en_us_guide_dashboardq.md":"085b25e1","en_us_guide_dashboard.md":"16cd09aa","en_us_guide_docker_build.md":"b3848339","en_us_guide_docker_install.md":"5289010c","en_us_guide_docker_precheck.md":"eac58da7","en_us_guide_docker_thanks.md":"efe98fe0","case_case3.md":"7d92b07b","guide_dashboardq.md":"3893e625","en_us_guide_lxd_precheck.md":"2e2a33cf","case_index.md":"24bc5502","guide_docker_build.md":"c036239b","en_us_guide_lxd_custom.md":"409cc27a","en_us_guide_lxd_install.md":"5fed8e1c","guide_docker_custom.md":"26e5d6da","guide_docker_install.md":"9c4dfe76","en_us_guide_lxd_qa.md":"56fc1b99","en_us_guide_pve_custom.md":"f36afe00","guide_docker_qa.md":"e3495596","case_case2.md":"d874c8dc","en_us_guide_lxd_lxc.md":"e9dae8c9","case_case7.md":"66976877","guide_lxd_precheck.md":"5b4a49b1","case_case6.md":"75b752e2","en_us_guide_pve_qa.md":"62caeb30","en_us_developer_index.md":"af61a53a","en_us_guide_pve_precheck.md":"05864ff5","guide_pve_qa.md":"f8dd54b6","guide_pve_lxc.md":"2a244f13","guide_pve_thanks.md":"126038c6","guide_lxd_custom.md":"60c43748","en_us_guide_lxd_extra_config.md":"3e98857d","en_us_guide_pve_thanks.md":"97d718bb","guide_lxd_install.md":"46740cb0","guide_lxd_thanks.md":"02a09d1b","guide_pve_custom.md":"5e626f3c","guide_dashboard.md":"a3c763b3","developer_l10n.md":"419f429a","guide_pve_install.md":"ae12d93c","developer_index.md":"686e6722","index.md":"d5f6c31c","guide_pve_precheck.md":"f6d114e8","en_us_guide_docker_custom.md":"edc0e200","case_case4.md":"1ee89607","guide_pve_kvm.md":"1d65178c","case_case1.md":"c45906da","en_us_guide_lxd_thanks.md":"74193152","en_us_index.md":"36eb8cfe","en_us_guide_pve_install.md":"a6804c51","guide_docker_precheck.md":"e146ac73","guide_lxd_lxc.md":"afc61ad7","case_case5.md":"2ace1f49","en_us_guide_pve_kvm.md":"856957d2","guide_lxd_qa.md":"1355c22f"}
