{"case_case2.md":"6efc02bd","en_us_guide_lxd_extra_config.md":"3cb50e64","developer_l10n.md":"ba2603e8","en_us_guide_lxd_thanks.md":"b1c57f68","developer_index.md":"160a11be","en_us_developer_l10n.md":"a2ece4d4","en_us_guide_lxd_lxc.md":"ca50b8e5","en_us_guide_lxd_precheck.md":"45db650b","case_index.md":"5c3fb1bf","en_us_guide_pve_install.md":"d237b333","en_us_guide_pve_lxc.md":"c8bea8c9","en_us_guide_pve_custom.md":"77f471b6","en_us_guide_pve_kvm.md":"6f377cff","en_us_developer_index.md":"aac54521","en_us_guide_lxd_qa.md":"bcadc321","en_us_guide_pve_qa.md":"a7b6a84d","en_us_guide_pve_thanks.md":"917c8115","en_us_index.md":"de71f491","en_us_guide_dashboard.md":"7cf4ed88","en_us_guide_dashboardq.md":"7220aba0","case_case3.md":"6e45cb3d","guide_dashboard.md":"cfedbe49","guide_docker_build.md":"6dcc765e","case_case4.md":"eb55f82b","case_case5.md":"3c296c38","en_us_guide_lxd_install.md":"3bc77251","en_us_guide_pve_precheck.md":"c50b027c","en_us_guide_docker_custom.md":"a1166681","en_us_guide_docker_install.md":"defb6c41","guide_pve_custom.md":"fba330bd","guide_dashboardq.md":"f121755b","en_us_guide_docker_build.md":"394ba496","en_us_guide_lxd_custom.md":"63420b98","guide_docker_qa.md":"42b1ae65","en_us_guide_docker_precheck.md":"2a5a56ec","en_us_guide_docker_qa.md":"c8bbbdd4","en_us_guide_docker_thanks.md":"f61d8e7e","guide_docker_thanks.md":"16131f69","guide_lxd_custom.md":"947409c7","guide_lxd_extra_config.md":"a96dc452","guide_lxd_install.md":"1f20ab5a","guide_lxd_lxc.md":"e1ca5ecd","guide_lxd_precheck.md":"9eb6a38e","guide_lxd_qa.md":"9cc8f205","guide_lxd_thanks.md":"ee372cde","case_case1.md":"82f737b3","guide_pve_kvm.md":"3d9d925d","guide_pve_install.md":"59128169","guide_pve_precheck.md":"60f8d7a0","guide_docker_custom.md":"b79a84a2","guide_pve_qa.md":"c510d42d","guide_pve_thanks.md":"5d976c16","index.md":"77aa5045","guide_pve_lxc.md":"2e7834aa","guide_docker_install.md":"a1277a43","guide_docker_precheck.md":"ea2aed79"}
