{"case_case3.md":"746c598f","case_case4.md":"e1d4f5f0","case_case5.md":"141244e5","case_index.md":"5405d495","developer_index.md":"3d5f75cd","developer_l10n.md":"baf11484","en_us_developer_index.md":"3643adbc","en_us_developer_l10n.md":"2785a321","en_us_guide_dashboard.md":"a1b698b2","en_us_guide_dashboardq.md":"bf9f4bcd","en_us_guide_docker_build.md":"6c9475d5","en_us_guide_docker_precheck.md":"3f0b2d09","en_us_guide_docker_qa.md":"e6269e05","en_us_guide_docker_thanks.md":"aad3154d","en_us_guide_lxd_extra_config.md":"5d9c655d","en_us_guide_lxd_install.md":"3c21858b","en_us_guide_lxd_lxc.md":"2f32dd01","en_us_guide_lxd_precheck.md":"35cfe98d","en_us_guide_lxd_qa.md":"7d4ce0be","en_us_guide_lxd_thanks.md":"ef284cd8","en_us_guide_pve_install.md":"1c81fe1f","en_us_guide_pve_kvm.md":"e7981840","index.md":"1cdc8f7b","case_case2.md":"8d295bc5","en_us_guide_pve_lxc.md":"925da836","en_us_guide_pve_precheck.md":"c62c0623","en_us_guide_pve_qa.md":"ed13b0e9","en_us_guide_pve_thanks.md":"984c72ad","en_us_index.md":"ff5146cb","guide_dashboard.md":"aa18eff0","guide_dashboardq.md":"2958a46f","guide_docker_build.md":"d27d5a66","guide_docker_install.md":"afc83520","guide_docker_precheck.md":"45ccd2af","guide_docker_qa.md":"e2fc9c57","guide_docker_thanks.md":"e51cd7d1","guide_lxd_extra_config.md":"306b4b1a","guide_lxd_install.md":"09c72da2","guide_lxd_lxc.md":"e0405753","guide_lxd_precheck.md":"acb522b9","guide_lxd_qa.md":"d21faf56","guide_lxd_thanks.md":"83bea245","guide_pve_install.md":"4acabd30","guide_pve_kvm.md":"e92db31c","guide_pve_lxc.md":"6fb74e2d","guide_pve_precheck.md":"5e81e0bb","guide_pve_qa.md":"bcfe7ea3","guide_pve_thanks.md":"49550b2d","en_us_guide_docker_install.md":"58dd5795","case_case1.md":"0c3cccf9"}
